json_logic/__init__.py
json-logic-py/json_logic.py
json-logic-py/__init__.py
json_logic-0.6.2.dist-info/METADATA
json_logic-0.6.2.dist-info/RECORD
json_logic-0.6.2.dist-info/top_level.txt
json_logic-0.6.2.dist-info/DESCRIPTION.rst
json_logic-0.6.2.dist-info/WHEEL
json_logic-0.6.2.dist-info/metadata.json
