Metadata-Version: 2.0
Name: json-logic
Version: 0.6.2
Summary: Build complex rules, serialize them as JSON, and execute them in Python
Home-page: https://github.com/nadirizr/json-logic-py
Author: nadir.izr
Author-email: nadir@soundmindtech.com
License: MIT
Keywords: json-logic
Platform: UNKNOWN
Classifier: Development Status :: 4 - Beta
Classifier: Intended Audience :: Developers
Classifier: Topic :: Software Development :: Libraries :: Python Modules
Classifier: License :: OSI Approved :: MIT License
Classifier: Programming Language :: Python :: 2
Classifier: Programming Language :: Python :: 2.6
Classifier: Programming Language :: Python :: 2.7
Classifier: Programming Language :: Python :: 3
Classifier: Programming Language :: Python :: 3.2
Classifier: Programming Language :: Python :: 3.3
Classifier: Programming Language :: Python :: 3.4
Provides-Extra: test
Requires-Dist: coverage; extra == 'test'
Provides-Extra: dev
Requires-Dist: check-manifest; extra == 'dev'
